neuronlinear/__init__.py
neuronlinear/model.py
neuronlinear-0.0.1.dist-info/LICENSE
neuronlinear-0.0.1.dist-info/METADATA
neuronlinear-0.0.1.dist-info/WHEEL
neuronlinear-0.0.1.dist-info/top_level.txt
neuronlinear-0.0.1.dist-info/RECORD
