Metadata-Version: 2.1
Name: neuronlinear
Version: 0.0.1
Summary: A small Perceptron package
Author-email: iamNagasatya <n.nagasatyasai@gmail.com>
Project-URL: Homepage, https://github.com/iamNagasatya/Perceptron
Project-URL: Bug Tracker, https://github.com/iamNagasatya/Perceptron/issues
Classifier: Programming Language :: Python :: 3
Classifier: License :: OSI Approved :: MIT License
Classifier: Operating System :: OS Independent
Requires-Python: >=3.6
License-File: LICENSE
Requires-Dist: joblib (==1.2.0)
Requires-Dist: numpy (==1.24.3)
Requires-Dist: pandas (==2.0.1)
